{
    "BOT-DATA-VERSION": "0.0.06",
    "serverOwner": "Nao-nyan",
    "serverOwnerID": 412213648916742145,
    "guildName": "Nao Nyan's Pocket Space",
    "guildID": 929403679071682620,
    "bdaysEnabled": false,
    "bdayChannelID": null,
    "bdayWishlistEnabled": false,
    "reactionRoles": {
        "MESSAGE ID": {
            "Max Roles": 0,
            "rr": {
                "EMOJI": "ROLE ID"
            }
        }
    },
    "users": {
        "USER ID": {
            "name": "USER NAME",
            "id": "USER ID",
            "blacklisted": false,
            "warnings": {
                "0": {
                    "warning": "reason"
                }
            }
        },
        "214169548138610689": {
            "name": "Wild_Hook",
            "id": 214169548138610689,
            "blacklisted": false,
            "warnings": {}
        },
        "127107242125164544": {
            "name": "G00ns3",
            "id": 127107242125164544,
            "blacklisted": false,
            "warnings": {}
        },
        "222715600768598019": {
            "name": "Ryu852VT",
            "id": 222715600768598019,
            "blacklisted": false,
            "warnings": {}
        },
        "920677929657180190": {
            "name": "Quest",
            "id": 920677929657180190,
            "blacklisted": false,
            "warnings": {}
        },
        "254427411729481739": {
            "name": "Chengthehybrid",
            "id": 254427411729481739,
            "blacklisted": false,
            "warnings": {}
        },
        "291030712671535115": {
            "name": "CORGI",
            "id": 291030712671535115,
            "blacklisted": false,
            "warnings": {}
        },
        "123456133368119296": {
            "name": "MirAei",
            "id": 123456133368119296,
            "blacklisted": false,
            "warnings": {}
        },
        "180401167887630336": {
            "name": "Karasumar",
            "id": 180401167887630336,
            "blacklisted": false,
            "warnings": {}
        },
        "412213648916742145": {
            "name": "Nao-nyan",
            "id": 412213648916742145,
            "blacklisted": false,
            "warnings": {}
        },
        "164466409353641985": {
            "name": "Ultra",
            "id": 164466409353641985,
            "blacklisted": false,
            "warnings": {}
        },
        "804109999194374215": {
            "name": "Shakubabu",
            "id": 804109999194374215,
            "blacklisted": false,
            "warnings": {}
        },
        "145904185974587392": {
            "name": "OctoBOO",
            "id": 145904185974587392,
            "blacklisted": false,
            "warnings": {}
        },
        "1006374761942757427": {
            "name": "RagRed",
            "id": 1006374761942757427,
            "blacklisted": false,
            "warnings": {}
        },
        "460727500830408705": {
            "name": "Marcezsa",
            "id": 460727500830408705,
            "blacklisted": false,
            "warnings": {}
        },
        "458627903211569162": {
            "name": "Ondrej",
            "id": 458627903211569162,
            "blacklisted": false,
            "warnings": {}
        },
        "194616572906700800": {
            "name": "StarSingerMLP",
            "id": 194616572906700800,
            "blacklisted": false,
            "warnings": {}
        },
        "238781623427006464": {
            "name": "Devestator",
            "id": 238781623427006464,
            "blacklisted": false,
            "warnings": {}
        },
        "313063081100050442": {
            "name": "Zboy06",
            "id": 313063081100050442,
            "blacklisted": false,
            "warnings": {}
        },
        "750591928751358023": {
            "name": "Asunakibou",
            "id": 750591928751358023,
            "blacklisted": false,
            "warnings": {}
        },
        "352525407997657089": {
            "name": "Thaum",
            "id": 352525407997657089,
            "blacklisted": false,
            "warnings": {}
        },
        "560941194184491009": {
            "name": "One Toasty Boi",
            "id": 560941194184491009,
            "blacklisted": false,
            "warnings": {}
        },
        "346991666315526145": {
            "name": "Nova Starsniper",
            "id": 346991666315526145,
            "blacklisted": false,
            "warnings": {}
        },
        "590313005133332500": {
            "name": "KawaiiKazmii",
            "id": 590313005133332500,
            "blacklisted": false,
            "warnings": {}
        },
        "1002132874914443316": {
            "name": "Hypeventure",
            "id": 1002132874914443316,
            "blacklisted": false,
            "warnings": {}
        },
        "258606198889250816": {
            "name": "Zetteru",
            "id": 258606198889250816,
            "blacklisted": false,
            "warnings": {}
        },
        "907581609887273002": {
            "name": "Eria Mitsuki",
            "id": 907581609887273002,
            "blacklisted": false,
            "warnings": {}
        },
        "199971049281028096": {
            "name": "AdreusVT",
            "id": 199971049281028096,
            "blacklisted": false,
            "warnings": {}
        },
        "416611174164070403": {
            "name": "Zhadow",
            "id": 416611174164070403,
            "blacklisted": false,
            "warnings": {}
        },
        "422368238983446528": {
            "name": "jkornacki the boop man",
            "id": 422368238983446528,
            "blacklisted": false,
            "warnings": {}
        },
        "481645293989920779": {
            "name": "Kaiabluq",
            "id": 481645293989920779,
            "blacklisted": false,
            "warnings": {}
        },
        "258682651844542465": {
            "name": "Lt.Blythe",
            "id": 258682651844542465,
            "blacklisted": false,
            "warnings": {}
        },
        "429406593164247069": {
            "name": "Yokopokomo",
            "id": 429406593164247069,
            "blacklisted": false,
            "warnings": {}
        },
        "639206022543704074": {
            "name": "Lepty",
            "id": 639206022543704074,
            "blacklisted": false,
            "warnings": {}
        },
        "701329437341384725": {
            "name": "Splitzer0",
            "id": 701329437341384725,
            "blacklisted": false,
            "warnings": {}
        },
        "219917934334574592": {
            "name": "macro2805",
            "id": 219917934334574592,
            "blacklisted": false,
            "warnings": {}
        },
        "422846591766888464": {
            "name": "Sandvich",
            "id": 422846591766888464,
            "blacklisted": false,
            "warnings": {
                "0": "Stop Being Horni",
                "1": "Stop changing your name",
                "2": "your mums a dude",
                "3": "stop drinking so many energy drinks!!",
                "4": "no more horni",
                "5": "no more horni",
                "6": "no more horni",
                "7": "no more horni",
                "8": "no more horni",
                "9": "no more horni",
                "10": "no more horni",
                "11": "no more horni",
                "12": "no more horni",
                "13": "no more horni",
                "14": "no more horni",
                "15": "no more horni",
                "16": "no more horni",
                "17": "cope",
                "18": "mald",
                "19": "seethe",
                "20": "STOP CHANGING YOUR NAME!!!!!"
            }
        },
        "948701702524116993": {
            "name": "femc2006",
            "id": 948701702524116993,
            "blacklisted": false,
            "warnings": {}
        },
        "110806349834645504": {
            "name": "Dim/Asuka",
            "id": 110806349834645504,
            "blacklisted": false,
            "warnings": {}
        },
        "884834513916682280": {
            "name": "Kazusa LockFind",
            "id": 884834513916682280,
            "blacklisted": false,
            "warnings": {}
        },
        "431431618528542725": {
            "name": "Unoriginalname101",
            "id": 431431618528542725,
            "blacklisted": false,
            "warnings": {}
        },
        "172395097705414656": {
            "name": "eivl",
            "id": 172395097705414656,
            "blacklisted": false,
            "warnings": {}
        },
        "373277979779792898": {
            "name": "r3tropi",
            "id": 373277979779792898,
            "blacklisted": false,
            "warnings": {}
        },
        "442126080640286721": {
            "name": "Hazmat With A Hat",
            "id": 442126080640286721,
            "blacklisted": false,
            "warnings": {}
        },
        "234674316631998473": {
            "name": "greasyjespaa",
            "id": 234674316631998473,
            "blacklisted": false,
            "warnings": {}
        },
        "944364002702659675": {
            "name": "JOUSS",
            "id": 944364002702659675,
            "blacklisted": false,
            "warnings": {}
        },
        "853732678825934918": {
            "name": "Tiramisu",
            "id": 853732678825934918,
            "blacklisted": false,
            "warnings": {}
        },
        "866994314524753931": {
            "name": "Neon Nya",
            "id": 866994314524753931,
            "blacklisted": false,
            "warnings": {}
        },
        "769288555062493204": {
            "name": "MrNiceGuy",
            "id": 769288555062493204,
            "blacklisted": false,
            "warnings": {}
        },
        "734428181880373349": {
            "name": "\ud835\udc77\ud835\udc93\ud835\udc90\ud835\udc85.\ud835\udc6f\ud835\udc96\ud835\udc90\ud835\udc8f\ud835\udc88\ud835\udc8c\ud835\udc82\ud83c\udfb9",
            "id": 734428181880373349,
            "blacklisted": false,
            "warnings": {}
        },
        "198874453361295360": {
            "name": "TheThirdHorsewoman",
            "id": 198874453361295360,
            "blacklisted": false,
            "warnings": {}
        },
        "596762809409208320": {
            "name": "CyclicHeadcrabs",
            "id": 596762809409208320,
            "blacklisted": false,
            "warnings": {}
        },
        "438387592178827264": {
            "name": "NotIntruder",
            "id": 438387592178827264,
            "blacklisted": false,
            "warnings": {}
        },
        "702661647017181334": {
            "name": "SilverCinder",
            "id": 702661647017181334,
            "blacklisted": false,
            "warnings": {}
        },
        "379020774931038218": {
            "name": "Kozumi",
            "id": 379020774931038218,
            "blacklisted": false,
            "warnings": {}
        },
        "392529274751418400": {
            "name": "Ethereal_Winter",
            "id": 392529274751418400,
            "blacklisted": false,
            "warnings": {}
        }
    }
}